<!-- Demo of the flasher behavior.  -->
<!-- Bubbles or fireflies move around and fade on and off  -->
<!-- Jim Salem 1/28/11 jsalem@gmail.com -->
<!-- Movement is pretty wonky. -->

<!---All configuration items contain a "Class" tag specifying the python class they represent, and an "Args" tag specifying the args to be passed in.-->
<LightInstallation>
    <InstallationConfiguration>
        <Defaults>
            <PixelMapper>simplemap</PixelMapper>
        </Defaults>
    </InstallationConfiguration>
    <PixelConfiguration>
        <InheritsFrom>layouts/60StripLayout.xml</InheritsFrom>
    </PixelConfiguration>
    <PixelMapperConfiguration>
        <PixelMapper>
            <Class>pixelmappers.SimpleMapper</Class>
            <Args>
                <Id>simplemap</Id>
                <CutoffDist>20</CutoffDist>
            </Args>
        </PixelMapper>
        <PixelMapper>
            <Class>pixelmappers.GaussianMapper</Class>
            <Args>
                <Id>gaussmap</Id>
                <CutoffDist>30</CutoffDist>
                <MinWeight>0.1</MinWeight>
                <Width>10</Width>
                <Height>1</Height>
            </Args>
        </PixelMapper>
    </PixelMapperConfiguration>
    <RendererConfiguration>
        <Renderer>
            <InheritsFrom>renderers/60StripSeq.xml</InheritsFrom>
        </Renderer>
        <Renderer>
            <InheritsFrom>renderers/Pygame.xml</InheritsFrom>
        </Renderer>
    </RendererConfiguration>
    <InputConfiguration>
        <InputElement>
            <Class>inputs.PygameInput</Class>
            <Args>
                <Id>pygameclick</Id>
                <RefreshInterval>10</RefreshInterval>
                <Clicks>True</Clicks>
            </Args>
        </InputElement>
        <InputElement>
            <Class>inputs.PygameInput</Class>
            <Args>
                <Id>pygamekey</Id>
                <RefreshInterval>10</RefreshInterval>
                <Keyboard>True</Keyboard>
            </Args>
        </InputElement>
        <InputElement>
            <Class>inputs.UDPInput</Class>
            <Args>
                <Id>udp</Id>
                <Port>3344</Port>
                <RefreshInterval>50</RefreshInterval>
            </Args>
        </InputElement>
    </InputConfiguration>

    <BehaviorConfiguration>
        <Behavior>
            <Class>behaviors.RandomSetBrightColorBehavior</Class>
            <Args>
                <Id>setbrightcolor</Id>
            </Args>
        </Behavior>
        <Behavior Id="decay">
            <InheritsFrom>behaviors/PixelDecay.xml</InheritsFrom>
        </Behavior>
        <Behavior>
            <Class>behaviors.RestrictLocation</Class>
            <Args>
                <Id>xbounce</Id>
                <Action>'{val}*-1'</Action>
                <ParamName>XStep</ParamName>
                <LocationRestriction>{x}&lt;0 or {x}&gt;800</LocationRestriction>
            </Args>
        </Behavior>
        <Behavior>
            <Class>behaviors.RestrictLocation</Class>
            <Args>
                <Id>ybounce</Id>
                <Action>'{val}*-1'</Action>
                <ParamName>YStep</ParamName>
                <LocationRestriction>{y}&lt;0 or {y}&gt;200</LocationRestriction>
            </Args>
        </Behavior>
	<Behavior>
	  <Class>behaviors.Flasher</Class>
	  <Args>
	    <Id>flasher</Id>
	  </Args>
	</Behavior>
        <Behavior>
            <Class>behaviors.BehaviorChain</Class>
            <Args>
                <Id>flashermovebounce</Id>
                <ChainedBehaviors>
                    <Id>randmovement</Id>
                    <Id>ybounce</Id>
                    <Id>xbounce</Id>
		            <Id>flasher</Id>
                </ChainedBehaviors>
            </Args>
        </Behavior>
        <Behavior>
            <Class>behaviors.Square</Class>
            <Args>
                <Id>square</Id>
                <Width>15</Width>
            </Args>
        </Behavior>
        <Behavior>
            <Class>behaviors.RandomWalk</Class>
            <Args>
                <Id>randmovement</Id>
                <StepSize>20</StepSize>
            </Args>
        </Behavior>
        <Behavior>
            <Class>behaviors.BehaviorChain</Class>
            <Args>
                <Id>runcolordecay</Id>
                <Inputs>
                    <Id>pygameclick</Id>
                </Inputs>
                <ChainedBehaviors>
                    <Id>setbrightcolor</Id>
                    <Id>mover</Id>
                    <Id>decay</Id>
                </ChainedBehaviors>
                <RecursiveHooks>{'mover':'flashermovebounce'}</RecursiveHooks>
                <RenderToScreen>True</RenderToScreen>
                <Mapper>gaussmap</Mapper>
            </Args>
        </Behavior>
        <Behavior>
            <Class>behaviors.ResponseMover</Class>
            <Args>
                <Id>mover</Id>
            </Args>
        </Behavior>
        <Behavior>
            <Class>behaviors.EchoBehavior</Class>
            <Args>
                <Id>echo</Id>
                <z-index>0</z-index>
	        	<Color>(90,90,90)</Color>
                <RenderToScreen>False</RenderToScreen>
            </Args>
        </Behavior>
    </BehaviorConfiguration>
</LightInstallation>
